JWSToolKit/Cube.py
JWSToolKit/Image.py
JWSToolKit/Spec.py
JWSToolKit/__init__.py
jwstoolkit-1.1.3.dist-info/licenses/LICENCE
jwstoolkit-1.1.3.dist-info/METADATA
jwstoolkit-1.1.3.dist-info/WHEEL
jwstoolkit-1.1.3.dist-info/top_level.txt
jwstoolkit-1.1.3.dist-info/RECORD
