Metadata-Version: 2.4
Name: JWSToolKit
Version: 1.1.3
Summary: A python package for handling JWST observations
Author-email: Valentin Delabrosse <valentin.delabrosse@univ-grenoble-alpes.fr>
License-File: LICENCE
Requires-Dist: numpy
Requires-Dist: matplotlib
Requires-Dist: astropy
Requires-Dist: tqdm
Requires-Dist: scipy
Dynamic: license-file
